py_asynq/__init__.py
py_asynq/client.py
py_asynq/constant.py
py_asynq/example.py
py_asynq/task.py
py_asynq/proto/__init__.py
py_asynq/proto/asynq_pb2.py
py_asynq-0.0.4.dist-info/LICENSE
py_asynq-0.0.4.dist-info/METADATA
py_asynq-0.0.4.dist-info/WHEEL
py_asynq-0.0.4.dist-info/top_level.txt
py_asynq-0.0.4.dist-info/RECORD
